honesty/__init__.py
honesty/__version__.py
honesty/api.py
honesty/archive.py
honesty/cache.py
honesty/checker.py
honesty/cmdline.py
honesty/releases.py
honesty-0.2.1.dist-info/LICENSE
honesty-0.2.1.dist-info/METADATA
honesty-0.2.1.dist-info/WHEEL
honesty-0.2.1.dist-info/entry_points.txt
honesty-0.2.1.dist-info/top_level.txt
honesty-0.2.1.dist-info/RECORD
