Metadata-Version: 2.1
Name: honesty
Version: 0.2.1
Summary: Double check sdist/bdist on pypi
Home-page: https://github.com/python-packaging/honesty/
Author: Tim Hatch
Author-email: tim@timhatch.com
License: MIT
Platform: UNKNOWN
Classifier: Development Status :: 4 - Beta
Classifier: Environment :: Console
Classifier: License :: OSI Approved :: Apache Software License
Classifier: Programming Language :: Python
Classifier: Programming Language :: Python :: 3
Classifier: Programming Language :: Python :: 3 :: Only
Classifier: Programming Language :: Python :: 3.6
Classifier: Programming Language :: Python :: 3.7
Classifier: Programming Language :: Python :: 3.8
Classifier: Topic :: Utilities
Requires-Python: >=3.6
Requires-Dist: aiohttp (>=3.6)
Requires-Dist: appdirs (>=1.4)
Requires-Dist: click (>=7.0)
Requires-Dist: infer-license (>=0.0.6)
Requires-Dist: dataclasses (>=0.7) ; python_version < "3.7"
